jupyterserverwidget/__init__.py
jupyterserverwidget/serverwidget.py
jupyterserverwidget/serverwidgetmagics.py
jupyter_server_widget-0.1.2.dist-info/LICENSE.txt
jupyter_server_widget-0.1.2.dist-info/METADATA
jupyter_server_widget-0.1.2.dist-info/WHEEL
jupyter_server_widget-0.1.2.dist-info/top_level.txt
jupyter_server_widget-0.1.2.dist-info/RECORD
