Metadata-Version: 2.1
Name: jupyter-server-widget
Version: 0.1.2
Summary: Jupyter Notebook %%magics and Widget to start and stop servers from a Cell
Home-page: https://github.com/srizzo/jupyter-server-widget
Author: Samuel Rizzo
Author-email: rizzolabs@gmail.com
License: MIT
Keywords: ipython,jupyter
Platform: UNKNOWN
Classifier: Intended Audience :: Developers
Classifier: Intended Audience :: System Administrators
Classifier: Intended Audience :: Science/Research
Classifier: Programming Language :: Python
Classifier: Programming Language :: Python :: 2.7
Classifier: Programming Language :: Python :: 3.7
Requires-Dist: ipython
Requires-Dist: jupyter
